xdrparser/__init__.py
xdrparser/cli.py
xdrparser/parser.py
xdrparser-1.3.1.dist-info/LICENSE
xdrparser-1.3.1.dist-info/METADATA
xdrparser-1.3.1.dist-info/WHEEL
xdrparser-1.3.1.dist-info/entry_points.txt
xdrparser-1.3.1.dist-info/top_level.txt
xdrparser-1.3.1.dist-info/RECORD
