Metadata-Version: 2.1
Name: xdrparser
Version: 1.3.1
Summary: Xdr parser for Kin's history files
Home-page: https://github.com/kinecosystem/xdrparser
Author: Ron Serruya
Author-email: ron.serruya@kik.com
License: UNKNOWN
Platform: UNKNOWN
Classifier: Programming Language :: Python :: 3
Classifier: License :: OSI Approved :: MIT License
Classifier: Operating System :: OS Independent
Requires-Python: >=3.4
Requires-Dist: Click (==6.7)
Requires-Dist: kin-base (==1.0.7)
